customgpt_client/__init__.py
customgpt_client/api/__init__.py
customgpt_client/api/citations/__init__.py
customgpt_client/api/citations/get_citation.py
customgpt_client/api/conversations/__init__.py
customgpt_client/api/conversations/create_conversation.py
customgpt_client/api/conversations/delete_conversation.py
customgpt_client/api/conversations/get_conversations.py
customgpt_client/api/conversations/messages_conversation.py
customgpt_client/api/conversations/send_message.py
customgpt_client/api/conversations/update_conversation.py
customgpt_client/api/limits/__init__.py
customgpt_client/api/limits/get_api_v1_limits_usage.py
customgpt_client/api/page_metadata/__init__.py
customgpt_client/api/page_metadata/get_metadata.py
customgpt_client/api/page_metadata/update_metadata.py
customgpt_client/api/pages/__init__.py
customgpt_client/api/pages/delete_page.py
customgpt_client/api/pages/get_pages.py
customgpt_client/api/pages/preview_citation.py
customgpt_client/api/pages/reindex_page.py
customgpt_client/api/project_plugins/__init__.py
customgpt_client/api/project_plugins/create_plugin.py
customgpt_client/api/project_plugins/get_plugin.py
customgpt_client/api/project_plugins/update_plugin.py
customgpt_client/api/project_settings/__init__.py
customgpt_client/api/project_settings/get_project_settings.py
customgpt_client/api/project_settings/update_project_settings.py
customgpt_client/api/projects/__init__.py
customgpt_client/api/projects/create_project.py
customgpt_client/api/projects/delete_project.py
customgpt_client/api/projects/get_project.py
customgpt_client/api/projects/list_projects.py
customgpt_client/api/projects/replicate_project.py
customgpt_client/api/projects/stats_project.py
customgpt_client/api/projects/update_project.py
customgpt_client/api/reports_analytics/__init__.py
customgpt_client/api/reports_analytics/analysis_reports.py
customgpt_client/api/reports_analytics/conversations_reports.py
customgpt_client/api/reports_analytics/queries_reports.py
customgpt_client-1.2.8.dist-info/METADATA
customgpt_client-1.2.8.dist-info/WHEEL
customgpt_client-1.2.8.dist-info/RECORD
